ssh_certificate_parser/__init__.py
ssh_certificate_parser/__main__.py
ssh_certificate_parser/errors.py
ssh_certificate_parser/parser_helpers.py
ssh_certificate_parser-1.6.0.dist-info/LICENSE.txt
ssh_certificate_parser-1.6.0.dist-info/METADATA
ssh_certificate_parser-1.6.0.dist-info/WHEEL
ssh_certificate_parser-1.6.0.dist-info/top_level.txt
ssh_certificate_parser-1.6.0.dist-info/RECORD
