Metadata-Version: 2.1
Name: ssh-certificate-parser
Version: 1.6.0
Summary: Python library for interacting with OpenSSH Certificates
Home-page: https://github.com/easypost/ssh_certificate_parser
Author: James Brown
Author-email: jbrown@easypost.com
License: ISC
Project-URL: Docs, https://ssh-certificate-parser.readthedocs.io/
Project-URL: Tracker, https://github.com/EasyPost/ssh_certificate_parser/issues
Project-URL: Source, https://github.com/EasyPost/ssh_certificate_parser
Classifier: Development Status :: 3 - Alpha
Classifier: Environment :: Console
Classifier: Programming Language :: Python
Classifier: Programming Language :: Python :: 3.6
Classifier: Programming Language :: Python :: 3.7
Classifier: Programming Language :: Python :: 3.8
Classifier: Programming Language :: Python :: 3.9
Classifier: Programming Language :: Python :: 3.10
Classifier: Programming Language :: Python :: 3.11
Classifier: Operating System :: POSIX
Classifier: Intended Audience :: Developers
Classifier: License :: OSI Approved :: ISC License (ISCL)
License-File: LICENSE.txt
Requires-Dist: attrs (>=16)
